tao/__init__.py
tao/abc/__init__.py
tao/abc/profile.py
tao/abc/trace_code.py
tao/abc/validate.py
tao/algebra/__init__.py
tao/analysis/__init__.py
tao/download/__init__.py
tao/drlhp/__init__.py
tao/gui/__init__.py
tao/gui/qt/__init__.py
tao/gui/qt/qt5.py
tao/gui/qt/qt6.py
tao/gui/qt/widgets/__init__.py
tao/gui/qt/widgets/rect.py
tao/gui/tkinterx/__init__.py
tao/gui/tkinterx/graph/__init__.py
tao/gui/tkinterx/graph/base.py
tao/gui/tkinterx/graph/selector.py
tao/gui/tkinterx/graph/shape.py
tao/gui/tkinterx/graph/window.py
tao/gui/tkinterx/tips.py
tao/gui/tkinterx/tooltip.py
tao/quantum/__init__.py
tao/quantum/graph/__init__.py
tao/quantum/graph/tree.py
tao/tasks/__init__.py
tao/tasks/utils.py
tao/te/__init__.py
tao/te/tensor.py
tao/testing/__init__.py
tao/timeitx.py
tao/tools/__init__.py
tao/tools/dashstyle/__init__.py
tao/tools/dashstyle/design/__init__.py
tao/tools/dashstyle/design/template.py
tao/tools/dashstyle/server.py
tao/tools/dashstyle/utils/__init__.py
tao/tools/dashstyle/utils/nav.py
tao/tools/sanstyle/__init__.py
tao/tools/sanstyle/display/__init__.py
tao/tools/sanstyle/display/_html.py
tao/tools/sanstyle/display/html.py
tao/tools/sanstyle/display/template.py
tao/tools/sanstyle/github/__init__.py
tao/tools/sanstyle/github/file.py
tao/tools/sanstyle/utils.py
tao/tools/write/__init__.py
tao/tools/write/_docs.py
tao/tools/write/doc.py
tao/tools/write/release.py
tao/utils/__init__.py
tao/utils/data.py
tao/utils/file.py
tao/utils/log_config.py
tao/utils/unzip.py
taolib-0.8.0.dist-info/METADATA
taolib-0.8.0.dist-info/WHEEL
taolib-0.8.0.dist-info/entry_points.txt
taolib-0.8.0.dist-info/licenses/LICENSE
taolib-0.8.0.dist-info/RECORD
